aihelpers/__init__.py
aihelpers-0.0.0.dist-info/METADATA
aihelpers-0.0.0.dist-info/WHEEL
aihelpers-0.0.0.dist-info/top_level.txt
aihelpers-0.0.0.dist-info/RECORD
