Metadata-Version: 2.1
Name: aihelpers
Version: 0.0.0
Summary: Coming soon
Author-email: Thomas Nelson <thomasnelson1@gmail.com>
